<?xml version="1.0"?>
<amberdata xmlns="http://schema.slothsoft.net/amber/amberdata"><tileset-lab-list><tileset-lab xmlns:amber="http://schema.slothsoft.net/amber/amberdata" xmlns:save="http://schema.slothsoft.net/savegame/editor" xmlns:html="http://www.w3.org/1999/xhtml" id="1" tile-count="27" info-count="39"/><tileset-lab xmlns:amber="http://schema.slothsoft.net/amber/amberdata" xmlns:save="http://schema.slothsoft.net/savegame/editor" xmlns:html="http://www.w3.org/1999/xhtml" id="2" tile-count="29" info-count="36"/><tileset-lab xmlns:amber="http://schema.slothsoft.net/amber/amberdata" xmlns:save="http://schema.slothsoft.net/savegame/editor" xmlns:html="http://www.w3.org/1999/xhtml" id="3" tile-count="24" info-count="31"/><tileset-lab xmlns:amber="http://schema.slothsoft.net/amber/amberdata" xmlns:save="http://schema.slothsoft.net/savegame/editor" xmlns:html="http://www.w3.org/1999/xhtml" id="4" tile-count="26" info-count="28"/><tileset-lab xmlns:amber="http://schema.slothsoft.net/amber/amberdata" xmlns:save="http://schema.slothsoft.net/savegame/editor" xmlns:html="http://www.w3.org/1999/xhtml" id="5" tile-count="31" info-count="33"/><tileset-lab xmlns:amber="http://schema.slothsoft.net/amber/amberdata" xmlns:save="http://schema.slothsoft.net/savegame/editor" xmlns:html="http://www.w3.org/1999/xhtml" id="6" tile-count="33" info-count="43"/><tileset-lab xmlns:amber="http://schema.slothsoft.net/amber/amberdata" xmlns:save="http://schema.slothsoft.net/savegame/editor" xmlns:html="http://www.w3.org/1999/xhtml" id="7" tile-count="27" info-count="26"/><tileset-lab xmlns:amber="http://schema.slothsoft.net/amber/amberdata" xmlns:save="http://schema.slothsoft.net/savegame/editor" xmlns:html="http://www.w3.org/1999/xhtml" id="8" tile-count="24" info-count="27"/><tileset-lab xmlns:amber="http://schema.slothsoft.net/amber/amberdata" xmlns:save="http://schema.slothsoft.net/savegame/editor" xmlns:html="http://www.w3.org/1999/xhtml" id="9" tile-count="35" info-count="33"/><tileset-lab xmlns:amber="http://schema.slothsoft.net/amber/amberdata" xmlns:save="http://schema.slothsoft.net/savegame/editor" xmlns:html="http://www.w3.org/1999/xhtml" id="10" tile-count="41" info-count="44"/><tileset-lab xmlns:amber="http://schema.slothsoft.net/amber/amberdata" xmlns:save="http://schema.slothsoft.net/savegame/editor" xmlns:html="http://www.w3.org/1999/xhtml" id="11" tile-count="36" info-count="38"/><tileset-lab xmlns:amber="http://schema.slothsoft.net/amber/amberdata" xmlns:save="http://schema.slothsoft.net/savegame/editor" xmlns:html="http://www.w3.org/1999/xhtml" id="12" tile-count="29" info-count="34"/><tileset-lab xmlns:amber="http://schema.slothsoft.net/amber/amberdata" xmlns:save="http://schema.slothsoft.net/savegame/editor" xmlns:html="http://www.w3.org/1999/xhtml" id="13" tile-count="22" info-count="22"/><tileset-lab xmlns:amber="http://schema.slothsoft.net/amber/amberdata" xmlns:save="http://schema.slothsoft.net/savegame/editor" xmlns:html="http://www.w3.org/1999/xhtml" id="14" tile-count="41" info-count="36"/><tileset-lab xmlns:amber="http://schema.slothsoft.net/amber/amberdata" xmlns:save="http://schema.slothsoft.net/savegame/editor" xmlns:html="http://www.w3.org/1999/xhtml" id="15" tile-count="49" info-count="46"/><tileset-lab xmlns:amber="http://schema.slothsoft.net/amber/amberdata" xmlns:save="http://schema.slothsoft.net/savegame/editor" xmlns:html="http://www.w3.org/1999/xhtml" id="16" tile-count="10" info-count="17"/><tileset-lab xmlns:amber="http://schema.slothsoft.net/amber/amberdata" xmlns:save="http://schema.slothsoft.net/savegame/editor" xmlns:html="http://www.w3.org/1999/xhtml" id="17" tile-count="49" info-count="54"/><tileset-lab xmlns:amber="http://schema.slothsoft.net/amber/amberdata" xmlns:save="http://schema.slothsoft.net/savegame/editor" xmlns:html="http://www.w3.org/1999/xhtml" id="18" tile-count="17" info-count="20"/><tileset-lab xmlns:amber="http://schema.slothsoft.net/amber/amberdata" xmlns:save="http://schema.slothsoft.net/savegame/editor" xmlns:html="http://www.w3.org/1999/xhtml" id="19" tile-count="46" info-count="47"/><tileset-lab xmlns:amber="http://schema.slothsoft.net/amber/amberdata" xmlns:save="http://schema.slothsoft.net/savegame/editor" xmlns:html="http://www.w3.org/1999/xhtml" id="26" tile-count="17" info-count="25"/><tileset-lab xmlns:amber="http://schema.slothsoft.net/amber/amberdata" xmlns:save="http://schema.slothsoft.net/savegame/editor" xmlns:html="http://www.w3.org/1999/xhtml" id="27" tile-count="23" info-count="23"/><tileset-lab xmlns:amber="http://schema.slothsoft.net/amber/amberdata" xmlns:save="http://schema.slothsoft.net/savegame/editor" xmlns:html="http://www.w3.org/1999/xhtml" id="28" tile-count="20" info-count="31"/><tileset-lab xmlns:amber="http://schema.slothsoft.net/amber/amberdata" xmlns:save="http://schema.slothsoft.net/savegame/editor" xmlns:html="http://www.w3.org/1999/xhtml" id="29" tile-count="19" info-count="20"/><tileset-lab xmlns:amber="http://schema.slothsoft.net/amber/amberdata" xmlns:save="http://schema.slothsoft.net/savegame/editor" xmlns:html="http://www.w3.org/1999/xhtml" id="30" tile-count="18" info-count="20"/><tileset-lab xmlns:amber="http://schema.slothsoft.net/amber/amberdata" xmlns:save="http://schema.slothsoft.net/savegame/editor" xmlns:html="http://www.w3.org/1999/xhtml" id="31" tile-count="22" info-count="22"/><tileset-lab xmlns:amber="http://schema.slothsoft.net/amber/amberdata" xmlns:save="http://schema.slothsoft.net/savegame/editor" xmlns:html="http://www.w3.org/1999/xhtml" id="32" tile-count="21" info-count="21"/><tileset-lab xmlns:amber="http://schema.slothsoft.net/amber/amberdata" xmlns:save="http://schema.slothsoft.net/savegame/editor" xmlns:html="http://www.w3.org/1999/xhtml" id="33" tile-count="6" info-count="9"/><tileset-lab xmlns:amber="http://schema.slothsoft.net/amber/amberdata" xmlns:save="http://schema.slothsoft.net/savegame/editor" xmlns:html="http://www.w3.org/1999/xhtml" id="34" tile-count="4" info-count="4"/><tileset-lab xmlns:amber="http://schema.slothsoft.net/amber/amberdata" xmlns:save="http://schema.slothsoft.net/savegame/editor" xmlns:html="http://www.w3.org/1999/xhtml" id="35" tile-count="20" info-count="22"/></tileset-lab-list></amberdata>
